tap_dimdate/__init__.py
tap_dimdate/schemas/calendar.json
tap_dimdate/streams.py
tap_dimdate/tap.py
tap_dimdate/tests/__init__.py
tap_dimdate/tests/test_core.py
tap_dimdate-0.1.0.dist-info/entry_points.txt
tap_dimdate-0.1.0.dist-info/WHEEL
tap_dimdate-0.1.0.dist-info/METADATA
tap_dimdate-0.1.0.dist-info/RECORD
