Metadata-Version: 2.1
Name: tap-dimdate
Version: 0.1.0
Summary: `tap-dimdate` is a Singer tap for generating a date dimension, built with the Meltano Singer SDK.
License: Apache 2.0
Keywords: ELT,DimDate
Author: Neil McGuigan
Requires-Python: >=3.7.1,<3.11
Classifier: License :: Other/Proprietary License
Classifier: Programming Language :: Python :: 3
Classifier: Programming Language :: Python :: 3.8
Classifier: Programming Language :: Python :: 3.9
Classifier: Programming Language :: Python :: 3.10
Requires-Dist: singer-sdk (>=0.11.1,<0.12.0)
